CHANGES.rst
README.rst
setup.cfg
setup.py
pyramid_facebook/__init__.py
pyramid_facebook/auth.py
pyramid_facebook/canvas.py
pyramid_facebook/credits.py
pyramid_facebook/events.py
pyramid_facebook/lib.py
pyramid_facebook/opengraph.py
pyramid_facebook/payments.py
pyramid_facebook/predicates.py
pyramid_facebook/real_time.py
pyramid_facebook/security.py
pyramid_facebook/utility.py
pyramid_facebook.egg-info/PKG-INFO
pyramid_facebook.egg-info/SOURCES.txt
pyramid_facebook.egg-info/dependency_links.txt
pyramid_facebook.egg-info/entry_points.txt
pyramid_facebook.egg-info/requires.txt
pyramid_facebook.egg-info/top_level.txt
pyramid_facebook/templates/opengraph_object.mako
pyramid_facebook/tests/__init__.py
pyramid_facebook/tests/functional/__init__.py
pyramid_facebook/tests/functional/test_canvas.py
pyramid_facebook/tests/functional/test_credits.py
pyramid_facebook/tests/functional/test_opengraph.py
pyramid_facebook/tests/functional/test_payments.py
pyramid_facebook/tests/functional/test_pfacebook_real_time.py
pyramid_facebook/tests/functional/test_real_time.py
pyramid_facebook/tests/functional/test_utility.py
pyramid_facebook/tests/integration/__init__.py
pyramid_facebook/tests/integration/test_payments.py
pyramid_facebook/tests/integration/test_real_time.py
pyramid_facebook/tests/unittests/__init__.py
pyramid_facebook/tests/unittests/test_auth.py
pyramid_facebook/tests/unittests/test_canvas.py
pyramid_facebook/tests/unittests/test_credits.py
pyramid_facebook/tests/unittests/test_events.py
pyramid_facebook/tests/unittests/test_lib.py
pyramid_facebook/tests/unittests/test_predicates.py
pyramid_facebook/tests/unittests/test_pyramid_facebook.py
pyramid_facebook/tests/unittests/test_real_time.py
pyramid_facebook/tests/unittests/test_security.py