Metadata-Version: 1.0
Name: pyramid-facebook
Version: 1.0.1
Summary: Pyramid routes and helpers for Facebook canvas applications
Home-page: UNKNOWN
Author: Hadrien David
Author-email: hadrien@ectobal.com
License: UNKNOWN
Platform: UNKNOWN
